asn1cipher/__init__.py
asn1cipher/block_cipher.py
asn1cipher/block_mode.py
asn1cipher/cipher.py
asn1cipher/cipher_adapter.py
asn1cipher/exceptions.py
asn1cipher/provider.py
asn1cipher/py.typed
asn1cipher/rc2_cipher.py
asn1cipher-0.1.0.dist-info/licenses/LICENSE
asn1cipher-0.1.0.dist-info/METADATA
asn1cipher-0.1.0.dist-info/WHEEL
asn1cipher-0.1.0.dist-info/top_level.txt
asn1cipher-0.1.0.dist-info/RECORD
