Metadata-Version: 2.4
Name: asn1cipher
Version: 0.1.0
Summary: A Python library for encrypting and decrypting ASN.1 encrypted content.
Author-email: Your Name <your.email@example.com>
License: Apache-2.0
Project-URL: Homepage, https://github.com/jc-lab/asn1cipher
Project-URL: Repository, https://github.com/jc-lab/asn1cipher
Project-URL: Documentation, https://github.com/jc-lab/asn1cipher
Project-URL: Bug Tracker, https://github.com/jc-lab/asn1cipher/issues
Keywords: asn1,encryption,cryptography,cms,pkcs
Classifier: Development Status :: 3 - Alpha
Classifier: Intended Audience :: Developers
Classifier: License :: OSI Approved :: Apache Software License
Classifier: Programming Language :: Python :: 3
Classifier: Programming Language :: Python :: 3.8
Classifier: Programming Language :: Python :: 3.9
Classifier: Programming Language :: Python :: 3.10
Classifier: Programming Language :: Python :: 3.11
Classifier: Programming Language :: Python :: 3.12
Classifier: Topic :: Security :: Cryptography
Requires-Python: >=3.8
License-File: LICENSE
Requires-Dist: asn1crypto>=1.5.1
Requires-Dist: cryptography>=46.0.3
Provides-Extra: dev
Requires-Dist: pytest>=8.4.2; extra == "dev"
Dynamic: license-file
